aas2openapi/__init__.py
aas2openapi/client/__init__.py
aas2openapi/client/aas_client.py
aas2openapi/client/submodel_client.py
aas2openapi/convert/__init__.py
aas2openapi/convert/convert_aas.py
aas2openapi/convert/convert_pydantic.py
aas2openapi/middleware/__init__.py
aas2openapi/middleware/graphql_routers.py
aas2openapi/middleware/middleware.py
aas2openapi/middleware/model_registry_api.py
aas2openapi/middleware/rest_routers.py
aas2openapi/models/__init__.py
aas2openapi/models/base.py
aas2openapi/util/__init__.py
aas2openapi/util/client_utils.py
aas2openapi/util/convert_util.py
aas2openapi/util/logging_util.py
aas2openapi-0.2.4.dist-info/LICENSE
aas2openapi-0.2.4.dist-info/METADATA
aas2openapi-0.2.4.dist-info/WHEEL
aas2openapi-0.2.4.dist-info/RECORD
