Metadata-Version: 2.1
Name: aas2openapi
Version: 0.2.4
Summary: 
License: MIT
Author: SebBehrendt
Requires-Python: >=3.10,<4.0
Classifier: License :: OSI Approved :: MIT License
Classifier: Programming Language :: Python :: 3
Classifier: Programming Language :: Python :: 3.10
Classifier: Programming Language :: Python :: 3.11
Requires-Dist: ba-syx-aas-repository-client (==2.0)
Requires-Dist: ba-syx-submodel-repository-client (==3.0)
Requires-Dist: basyx-python-sdk (>=1.0.0,<2.0.0)
Requires-Dist: email-validator (>=2.0.0.post2,<3.0.0)
Requires-Dist: fastapi (==0.99.1)
Requires-Dist: graphene-pydantic (>=0.4.2,<0.5.0)
Requires-Dist: openapi-python-client (>=0.14.1,<0.15.0)
Requires-Dist: pydantic (>=1.10.9,<2.0.0)
Requires-Dist: starlette-graphene3 (>=0.6.0,<0.7.0)
Requires-Dist: strawberry-graphql[debug-server] (>=0.199.0,<0.200.0)
Requires-Dist: uvicorn[standard] (>=0.21.0,<0.22.0)
Requires-Dist: websocket (>=0.2.1,<0.3.0)
